examples/__init__.py
examples/basic.py
prosonix/__init__.py
prosonix/__version__.py
prosonix/errors.py
prosonix/sonolab.py
prosonix-1.0.1.dist-info/LICENSE
prosonix-1.0.1.dist-info/METADATA
prosonix-1.0.1.dist-info/WHEEL
prosonix-1.0.1.dist-info/top_level.txt
prosonix-1.0.1.dist-info/RECORD
