Metadata-Version: 2.1
Name: prosonix
Version: 1.0.1
Summary: Unofficial Python package to control Prosonix products. We are not affiliated with Prosonix.
Home-page: https://gitlab.com/heingroup/prosonix
Author: Veronica Lai // Hein Group
License: UNKNOWN
Platform: UNKNOWN
Classifier: Programming Language :: Python :: 3
Requires-Python: >=3.6
Requires-Dist: ftdi-serial
